[ {
	"hero_id": 1,
	"name": "Alfonse",
	"basehp": 43,
	"baseatk": 35,
	"basespd": 25,
	"basedef": 32,
	"baseres": 22,
	"color": "Red",
	"weapontype": "Sword",
	"movetype": "infantry"
},
 {
    "hero:id": 2,
    "name": "Caeda",
    "basehp": 36,
    "baseatk": 26,
    "basespd": 37,
    "basedef": 24,
    "baseres": 34,
    "color": "Red",
    "weapontype": "Sword",
    "movetype": "flying"
},{
    "hero:id: 3,
    "name": "Cain",
    "basehp": 42,
    "baseatk": 32,
    "basespd": 32,
    "basedef": 27,
    "baseres": 21,
    "color": "Red",
    "weapontype": "Sword",
    "movetype": "cavalry"

},{
    "hero:id: 4,
    "name": "Chrom",
    "basehp": 47,
    "baseatk": 37,
    "basespd": 25,
    "basedef": 31,
    "baseres": 17,
    "color": "Red",
    "weapontype": "Sword",
    "movetype": "infanty"

},{
    "hero:id: 5,
    "name": "Corrin (M)",
    "basehp": 42,
    "baseatk": 32,
    "basespd": 32,
    "basedef": 28,
    "baseres": 24,
    "color": "Red",
    "weapontype": "Sword",
    "movetype": "infantry"

},{
    "hero:id: 6,
    "name": "Draug",
    "basehp": 50,
    "baseatk": 30,
    "basespd": 32,
    "basedef": 39,
    "baseres": 18,
    "color": "Red",
    "weapontype": "Sword",
    "movetype": "armored"

},{
    "hero:id: 7,
    "name": "Eirika",
    "basehp": 42,
    "baseatk": 26,
    "basespd": 35,
    "basedef": 26,
    "baseres": 28,
    "color": "Red",
    "weapontype": "Sword",
    "movetype": "infantry"

},{
    "hero:id: 8,
    "name": "Eldigan",
    "basehp": 45,
    "baseatk": 32,
    "basespd": 24,
    "basedef": 34,
    "baseres": 19,
    "color": "Red",
    "weapontype": "Sword",
    "movetype": "cavalry"

},{
    "hero:id: 9,
    "name": "Eliwood",
    "basehp": 39,
    "baseatk": 31,
    "basespd": 30,
    "basedef": 23,
    "baseres": 32,
    "color": "Red",
    "weapontype": "Sword",
    "movetype": "cavalry"

},{
    "hero:id: 10,
    "name": "Fir",
    "basehp": 41,
    "baseatk": 25,
    "basespd": 36,
    "basedef": 24,
    "baseres": 31,
    "color": "Red",
    "weapontype": "Sword",
    "movetype": "infantry"

},{
    "hero:id: 11,
    "name": "Hana",
    "basehp": 37,
    "baseatk": 35,
    "basespd": 36,
    "basedef": 23,
    "baseres": 26,
    "color": "Red",
    "weapontype": "Sword",
    "movetype": "infantry"

},{
    "hero:id: 12,
    "name": "Henry",
    "basehp": 45,
    "baseatk": 23,
    "basespd": 22,
    "basedef": 32,
    "baseres": 25,
    "color": "Red",
    "weapontype": "Redtome",
    "movetype": "infantry"

},{
    "hero:id: 13,
    "name": "Hitana",
    "basehp": 47,
    "baseatk": 32,
    "basespd": 24,
    "basedef": 36,
    "baseres": 18,
    "color": "Red",
    "weapontype": "Sword",
    "movetype": "infantry"

},{
    "hero:id: 14,
    "name": "Karel",
    "basehp": 47,
    "baseatk": 30,
    "basespd": 35,
    "basedef": 25,
    "baseres": 20,
    "color": "Red",
    "weapontype": "Sword",
    "movetype": "infantry"

},{
    "hero:id: 15,
    "name": "Laslow",
    "basehp": 44,
    "baseatk": 35,
    "basespd": 26,
    "basedef": 30,
    "baseres": 22,
    "color": "Red",
    "weapontype": "Sword",
    "movetype": "infantry"

},{
    "hero:id: 16,
    "name": "Leo",
    "basehp": 39,
    "baseatk": 29,
    "basespd": 22,
    "basedef": 25,
    "baseres": 30,
    "color": "Red",
    "weapontype": "Redtome",
    "movetype": "Cavalry"

},{
    "hero:id: 17,
    "name": "Lilina",
    "basehp": 35,
    "baseatk": 37,
    "basespd": 25,
    "basedef": 19,
    "baseres": 31,
    "color": "Red",
    "weapontype": "Redtome",
    "movetype": "Infantry"

},{
    "hero:id: 18,
    "name": "Lon'Qu",
    "basehp": 45,
    "baseatk": 29,
    "basespd": 39,
    "basedef": 22,
    "baseres": 22,
    "color": "Red",
    "weapontype": "Sword",
    "movetype": "Infantry"

},{
    "hero:id: 19,
    "name": "Lucina",
    "basehp": 43,
    "baseatk": 34,
    "basespd": 36,
    "basedef": 25,
    "baseres": 19,
    "color": "Red",
    "weapontype": "Sword",
    "movetype": "Infantry"

},{
    "hero:id: 20,
    "name": "Lyn",
    "basehp": 37,
    "baseatk": 28,
    "basespd": 37,
    "basedef": 26,
    "baseres": 29,
    "color": "Red",
    "weapontype": "Sword",
    "movetype": "Infantry"

},{
    "hero:id: 21,
    "name": "Marth",
    "basehp": 41,
    "baseatk": 31,
    "basespd": 34,
    "basedef": 29,
    "baseres": 23,
    "color": "Red",
    "weapontype": "Sword",
    "movetype": "Infantry"

},{
    "hero:id: 22,
    "name": "Ogma",
    "basehp": 47,
    "baseatk": 35,
    "basespd": 34,
    "basedef": 28,
    "baseres": 13,
    "color": "Red",
    "weapontype": "Sword",
    "movetype": "Infantry"

},{
    "hero:id: 23,
    "name": "Olivia",
    "basehp": 36,
    "baseatk": 28,
    "basespd": 33,
    "basedef": 27,
    "baseres": 26,
    "color": "Red",
    "weapontype": "Sword",
    "movetype": "Infantry"

},{
    "hero:id: 24,
    "name": "Palla",
    "basehp": 42,
    "baseatk": 31,
    "basespd": 31,
    "basedef": 28,
    "baseres": 26,
    "color": "Red",
    "weapontype": "Sword",
    "movetype": "Flier"

},{
    "hero:id: 25,
    "name": "Raigh",
    "basehp": 36,
    "baseatk": 32,
    "basespd": 29,
    "basedef": 22,
    "baseres": 29,
    "color": "Red",
    "weapontype": "Redtome",
    "movetype": "Infantry"

},{
    "hero:id: 26,
    "name": "Roy",
    "basehp": 44,
    "baseatk": 30,
    "basespd": 31,
    "basedef": 25,
    "baseres": 28,
    "color": "Red",
    "weapontype": "Sword",
    "movetype": "Infantry"

},{
    "hero:id: 27,
    "name": "Ryoma",
    "basehp": 41,
    "baseatk": 34,
    "basespd": 35,
    "basedef": 27,
    "baseres": 21,
    "color": "Red",
    "weapontype": "Sword",
    "movetype": "Infantry"

},{
    "hero:id: 28,
    "name": "Sanaki",
    "basehp": ,
    "baseatk": ,
    "basespd": ,
    "basedef": ,
    "baseres": ,
    "color": "Red",
    "weapontype": "Redtome",
    "movetype": "Infantry"

},{
    "hero:id: 29,
    "name": "Selena",
    "basehp": 33,
    "baseatk": 37,
    "basespd": 26,
    "basedef": 17,
    "baseres": 34,
    "color": "Red",
    "weapontype": "Sword",
    "movetype": "Infantry"

},{
    "hero:id: 30,
    "name": "Seliph",
    "basehp": 47,
    "baseatk": 34,
    "basespd": 24,
    "basedef": 30,
    "baseres": 22,
    "color": "Red",
    "weapontype": "Sword",
    "movetype": "Infantry"

},{
    "hero:id: 31,
    "name": "Sophia",
    "basehp": 40,
    "baseatk": 33,
    "basespd": 19,
    "basedef": 28,
    "baseres": 29,
    "color": "Red",
    "weapontype": "Redtome",
    "movetype": "Infantry"

},{
    "hero:id: 32,
    "name": "Stahl",
    "basehp": 45,
    "baseatk": 31,
    "basespd": 26,
    "basedef": 30,
    "baseres": 22,
    "color": "Red",
    "weapontype": "Sword",
    "movetype": "Cavalry"

},{
    "hero:id: 33,
    "name": "Tharja",
    "basehp": 39,
    "baseatk": 32,
    "basespd": 34,
    "basedef": 23,
    "baseres": 20,
    "color": "Red",
    "weapontype": "Redtome",
    "movetype": "Infantry"

},{
    "hero:id: 34,
    "name": "Tiki (Adult)",
    "basehp": 40,
    "baseatk": 35,
    "basespd": 23,
    "basedef": 35,
    "baseres": 24,
    "color": "Red",
    "weapontype": "Dragon",
    "movetype": "Infantry"

},{
    "hero:id: 35,
    "name": "Tiki (Young)",
    "basehp": 41,
    "baseatk": 31,
    "basespd": 30,
    "basedef": 32,
    "baseres": 29,
    "color": "Red",
    "weapontype": "Dragon",
    "movetype": "Infantry"

},{
    "hero:id: 36,
    "name": "Anna",
    "basehp": 41,
    "baseatk": 29,
    "basespd": 38,
    "basedef": 22,
    "baseres": 28,
    "color": "Green",
    "weapontype": "Axe",
    "movetype": "Infantry"

},{
    "hero:id: 37,
    "name": "Arthur",
    "basehp": 43,
    "baseatk": 32,
    "basespd": 29,
    "basedef": 30,
    "baseres": 24,
    "color": "Green",
    "weapontype": "Axe",
    "movetype": "Infantry"

},{
    "hero:id: 38,
    "name": "Barst",
    "basehp": 46,
    "baseatk": 33,
    "basespd": 32,
    "basedef": 30,
    "baseres": 17,
    "color": "Green",
    "weapontype": "Axe",
    "movetype": "Infantry"

},{
    "hero:id: 39,
    "name": "Bartre",
    "basehp": 49,
    "baseatk": 36,
    "basespd": 25,
    "basedef": 33,
    "baseres": 13,
    "color": "Green",
    "weapontype": "Axe",
    "movetype": "Infantry"

},{
    "hero:id: 40,
    "name": "Beruka",
    "basehp": 46,
    "baseatk": 29,
    "basespd": 23,
    "basedef": 37,
    "baseres": 22,
    "color": "Green",
    "weapontype": "Axe",
    "movetype": "Flier"

},{
    "hero:id: 41,
    "name": "Camilla",
    "basehp": 37,
    "baseatk": 30,
    "basespd": 32,
    "basedef": 28,
    "baseres": 31,
    "color": "Green",
    "weapontype": "Axe",
    "movetype": "Flier"

},{
    "hero:id: 42,
    "name": "Cecilia",
    "basehp": 36,
    "baseatk": 32,
    "basespd": 25,
    "basedef": 22,
    "baseres": 29,
    "color": "Green",
    "weapontype": "Greentome",
    "movetype": "Cavalry"

},{
    "hero:id: 43,
    "name": "Cherche",
    "basehp": 46,
    "baseatk": 38,
    "basespd": 25,
    "basedef": 32,
    "baseres": 16,
    "color": "Green",
    "weapontype": "Axe",
    "movetype": "Flier"

},{
    "hero:id: 44,
    "name": "Fae",
    "basehp": 46,
    "baseatk": 33,
    "basespd": 28,
    "basedef": 25,
    "baseres": 30,
    "color": "Green",
    "weapontype": "Dragon",
    "movetype": "Infantry"

},{
    "hero:id: 45,
    "name": "Frederick",
    "basehp": 43,
    "baseatk": 35,
    "basespd": 25,
    "basedef": 36,
    "baseres": 14,
    "color": "Green",
    "weapontype": "Axe",
    "movetype": "Cavalry"
},{
    "hero:id: 46,
    "name": "Gunter",
    "basehp": 43,
    "baseatk": 32,
    "basespd": 24,
    "basedef": 33,
    "baseres": 18,
    "color": "Green",
    "weapontype": "Axe",
    "movetype": "Cavalry"

},{
    "hero:id: 47,
    "name": "Hawkeye",
    "basehp": 45,
    "baseatk": .33,
    "basespd": 22,
    "basedef": 28,
    "baseres": 30,
    "color": "Green",
    "weapontype": "Axe",
    "movetype": "Infantry"

},{
    "hero:id: 48,
    "name": "Hector",
    "basehp": 52,
    "baseatk": 36,
    "basespd": 24,
    "basedef": 37,
    "baseres": 19,
    "color": "Green",
    "weapontype": "Axe",
    "movetype": "Armored"

},{
    "hero:id: 49,
    "name": "Julia",
    "basehp": 38,
    "baseatk": 35,
    "basespd": 26,
    "basedef": 17,
    "baseres": 32,
    "color": "Green",
    "weapontype": "Greentome",
    "movetype": "Infantry"

},{
    "hero:id: 50,
    "name": "Merric",
    "basehp": 43,
    "baseatk": 26,
    "basespd": 32,
    "basedef": 28,
    "baseres": 19,
    "color": "Green",
    "weapontype": "Greentome",
    "movetype": "Infantry"

},{
    "hero:id: 51,
    "name": "Minerva",
    "basehp": 40,
    "baseatk": 31,
    "basespd": 33,
    "basedef": 32,
    "baseres": 22,
    "color": "Green",
    "weapontype": "Axe",
    "movetype": "Flier"

},{
    "hero:id: 52,
    "name": "Narcian",
    "basehp": 42,
    "baseatk": 29,
    "basespd": 29,
    "basedef": 32,
    "baseres": 26,
    "color": "Green",
    "weapontype": "Axe",
    "movetype": "Flier"

},{
    "hero:id: 53,
    "name": "Nino",
    "basehp": 33,
    "baseatk": 33,
    "basespd": 36,
    "basedef": 19,
    "baseres": 26,
    "color": "Green",
    "weapontype": "Greentome",
    "movetype": "Infantry"

},{
    "hero:id: 54,
    "name": "Raven",
    "basehp": 41,
    "baseatk": 34,
    "basespd": 35,
    "basedef": 25,
    "baseres": 22,
    "color": "Green",
    "weapontype": "Axe",
    "movetype": "Infantry"

},{
    "hero:id: 55,
    "name": "Robin (F)",
    "basehp": 40,
    "baseatk": 29,
    "basespd": 29,
    "basedef": 29,
    "baseres": 22,
    "color": "Green",
    "weapontype": "Greentome",
    "movetype": "Infantry"

},{
    "hero:id: 56,
    "name": "Sheena",
    "basehp": 45,
    "baseatk": 30,
    "basespd": 25,
    "basedef": 36,
    "baseres": 33,
    "color": "Green",
    "weapontype": "Axe",
    "movetype": "Infantry"

},{
    "hero:id: 57,
    "name": "Abel",
    "basehp": 39,
    "baseatk": 33,
    "basespd": 32,
    "basedef": 25,
    "baseres": 25,
    "color": "Blue",
    "weapontype": "Lance",
    "movetype": "Cavalry"

},{
    "hero:id: 58,
    "name": "Azura",
    "basehp": 36,
    "baseatk": 31,
    "basespd": 33,
    "basedef": 21,
    "baseres": 28,
    "color": "Blue",
    "weapontype": "Lance",
    "movetype": "Infantry"

},{
    "hero:id: 59,
    "name": "Catria",
    "basehp": 39,
    "baseatk": 31,
    "basespd": 24,
    "basedef": 29,
    "baseres": 25,
    "color": "Blue",
    "weapontype": "Lance",
    "movetype": "Flier"

},{
    "hero:id: 60,
    "name": "Cordelia",
    "basehp": 40,
    "baseatk": 35,
    "basespd": 35,
    "basedef": 22,
    "baseres": 25,
    "color": "Blue",
    "weapontype": "Lance",
    "movetype": "Flier"

},{
    "hero:id: 61,
    "name": "Corrin (F)",
    "basehp": 41,
    "baseatk": 27,
    "basespd": 34,
    "basedef": 34,
    "baseres": 21,
    "color": "Blue",
    "weapontype": "Dragon",
    "movetype": "Infantry"

},{
    "hero:id: 62,
    "name": "Donnel",
    "basehp": 43,
    "baseatk": 35,
    "basespd": 29,
    "basedef": 32,
    "baseres": 23,
    "color": "Blue",
    "weapontype": "Lance",
    "movetype": "Infantry"

},{
    "hero:id: 63,
    "name": "Effie",
    "basehp": 50,
    "baseatk": 40,
    "basespd": 22,
    "basedef": 33,
    "baseres": 23,
    "color": "Blue",
    "weapontype": "Lance",
    "movetype": "Armored"

},{
    "hero:id: 64,
    "name": "Ephraim",
    "basehp": 45,
    "baseatk": 35,
    "basespd": 25,
    "basedef": 32,
    "baseres": 20,
    "color": "Blue",
    "weapontype": "Lance",
    "movetype": "Infantry"

},{
    "hero:id: 65,
    "name": "Est",
    "basehp": 36,
    "baseatk": 35,
    "basespd": 30,
    "basedef": 24,
    "baseres": 32,
    "color": "Blue",
    "weapontype": "Lance",
    "movetype": "Flier"

},{
    "hero:id: 66,
    "name": "Florina",
    "basehp": 42,
    "baseatk": 29,
    "basespd": 27,
    "basedef": 25,
    "baseres": 34,
    "color": "Blue",
    "weapontype": "Lance",
    "movetype": "Flier"

},{
    "hero:id: 67,
    "name": "Gwendolyn",
    "basehp": 49,
    "baseatk": 30,
    "basespd": 24,
    "basedef": 38,
    "baseres": 28,
    "color": "Blue",
    "weapontype": "Lance",
    "movetype": "Armored"

},{
    "hero:id: 68,
    "name": "Hinoka",
    "basehp": 41,
    "baseatk": 35,
    "basespd": 32,
    "basedef": 25,
    "baseres": 24,
    "color": "Blue",
    "weapontype": "Lance",
    "movetype": "Flier"

},{
    "hero:id: 69,
    "name": "Jagen",
    "basehp": 37,
    "baseatk": 27,
    "basespd": 24,
    "basedef": 25,
    "baseres": 35,
    "color": "Blue",
    "weapontype": "Lance",
    "movetype": "Cavalry"

},{
    "hero:id: 70,
    "name": "Linde",
    "basehp": 35,
    "baseatk": 35,
    "basespd": 36,
    "basedef": 14,
    "baseres": 27,
    "color": "Blue",
    "weapontype": "Bluetome",
    "movetype": "Infantry"

},{
    "hero:id: 71,
    "name": "Ninian",
    "basehp": 42,
    "baseatk": 24,
    "basespd": 33,
    "basedef": 23,
    "baseres": 27,
    "color": "Blue",
    "weapontype": "Dragon",
    "movetype": "Infantry"

},{
    "hero:id: 72,
    "name": "Nowi",
    "basehp": 45,
    "baseatk": 34,
    "basespd": 27,
    "basedef": 30,
    "baseres": 27,
    "color": "Blue",
    "weapontype": "Dragon",
    "movetype": "Infantry"

},{
    "hero:id: 73,
    "name": "Oboro",
    "basehp": 40,
    "baseatk": 32,
    "basespd": 26,
    "basedef": 35,
    "baseres": 24,
    "color": "Blue",
    "weapontype": "Lance",
    "movetype": "Infantry"
},{
    "hero:id: 74,
    "name": "Odin",
    "basehp": 22,
    "baseatk": 32,
    "basespd": 32,
    "basedef": 25,
    "baseres": 25,
    "color": "Blue",
    "weapontype": "Bluetome",
    "movetype": "Infantry"

},{
    "hero:id: 75,
    "name": "Olwen",
    "basehp": 34,
    "baseatk": 26,
    "basespd": 34,
    "basedef": 20,
    "baseres": 30,
    "color": "Blue",
    "weapontype": "Bluetome",
    "movetype": "Cavalry"

},{
    "hero:id: 76,
    "name": "Peri",
    "basehp": 35,
    "baseatk": 33,
    "basespd": 33,
    "basedef": 23,
    "baseres": 30,
    "color": "Blue",
    "weapontype": "Lance",
    "movetype": "Cavalry"

},{
    "hero:id: 77,
    "name": "Reinhardt",
    "basehp": 38,
    "baseatk": 32,
    "basespd": 23,
    "basedef": 27,
    "baseres": 25,
    "color": "Blue",
    "weapontype": "Bluetome",
    "movetype": "Cavalry"

},{
    "hero:id: 78,
    "name": "Robin (M)",
    "basehp": 40,
    "baseatk": 29,
    "basespd": 29,
    "basedef": 29,
    "baseres": 22,
    "color": "Blue",
    "weapontype": "Lance",
    "movetype": "Infantry"

},{
    "hero:id: 79,
    "name": "Shanna",
    "basehp": 39,
    "baseatk": 30,
    "basespd": 35,
    "basedef": 25,
    "baseres": 29,
    "color": "Blue",
    "weapontype": "Lance",
    "movetype": "Flier"
},{
    "hero:id: 80,
    "name": "Sharena",
    "basehp": ,
    "baseatk": ,
    "basespd": ,
    "basedef": ,
    "baseres": ,
    "color": "",
    "weapontype": "",
    "movetype": ""

},{
    "hero:id: 81,
    "name": "Subaki",
    "basehp": ,
    "baseatk": ,
    "basespd": ,
    "basedef": ,
    "baseres": ,
    "color": "",
    "weapontype": "",
    "movetype": ""

},{
    "hero:id: 82,
    "name": "Sully",
    "basehp": ,
    "baseatk": ,
    "basespd": ,
    "basedef": ,
    "baseres": ,
    "color": "",
    "weapontype": "",
    "movetype": ""

},{
    "hero:id: 83,
    "name": "Ursula",
    "basehp": ,
    "baseatk": ,
    "basespd": ,
    "basedef": ,
    "baseres": ,
    "color": "",
    "weapontype": "",
    "movetype": ""

},{
    "hero:id: 84,
    "name": "Azama",
    "basehp": ,
    "baseatk": ,
    "basespd": ,
    "basedef": ,
    "baseres": ,
    "color": "",
    "weapontype": "",
    "movetype": ""

},{
    "hero:id: 85,
    "name": "Clarine",
    "basehp": ,
    "baseatk": ,
    "basespd": ,
    "basedef": ,
    "baseres": ,
    "color": "",
    "weapontype": "",
    "movetype": ""

},{
    "hero:id: 86,
    "name": "Elise",
    "basehp": ,
    "baseatk": ,
    "basespd": ,
    "basedef": ,
    "baseres": ,
    "color": "",
    "weapontype": "",
    "movetype": ""

},{
    "hero:id: 87,
    "name": "Felicia",
    "basehp": ,
    "baseatk": ,
    "basespd": ,
    "basedef": ,
    "baseres": ,
    "color": "",
    "weapontype": "",
    "movetype": ""

},{
    "hero:id: 88,
    "name": "Gaius",
    "basehp": ,
    "baseatk": ,
    "basespd": ,
    "basedef": ,
    "baseres": ,
    "color": "",
    "weapontype": "",
    "movetype": ""

},{
    "hero:id: 89,
    "name": "Gordin",
    "basehp": ,
    "baseatk": ,
    "basespd": ,
    "basedef": ,
    "baseres": ,
    "color": "",
    "weapontype": "",
    "movetype": ""

},{
    "hero:id: 90,
    "name": "Jaffar",
    "basehp": ,
    "baseatk": ,
    "basespd": ,
    "basedef": ,
    "baseres": ,
    "color": "",
    "weapontype": "",
    "movetype": ""

},{
    "hero:id: 91,
    "name": "Jackob",
    "basehp": ,
    "baseatk": ,
    "basespd": ,
    "basedef": ,
    "baseres": ,
    "color": "",
    "weapontype": "",
    "movetype": ""

},{
    "hero:id: 92,
    "name": "Jeorge",
    "basehp": ,
    "baseatk": ,
    "basespd": ,
    "basedef": ,
    "baseres": ,
    "color": "",
    "weapontype": "",
    "movetype": ""

},{
    "hero:id: 93,
    "name": "Kagero",
    "basehp": ,
    "baseatk": ,
    "basespd": ,
    "basedef": ,
    "baseres": ,
    "color": "",
    "weapontype": "",
    "movetype": ""

},{
    "hero:id: 94,
    "name": "Klein",
    "basehp": ,
    "baseatk": ,
    "basespd": ,
    "basedef": ,
    "baseres": ,
    "color": "",
    "weapontype": "",
    "movetype": ""

},{
    "hero:id: 95,
    "name": "Lachesis",
    "basehp": ,
    "baseatk": ,
    "basespd": ,
    "basedef": ,
    "baseres": ,
    "color": "",
    "weapontype": "",
    "movetype": ""

},{
    "hero:id: 96,
    "name": "Lissa",
    "basehp": ,
    "baseatk": ,
    "basespd": ,
    "basedef": ,
    "baseres": ,
    "color": "",
    "weapontype": "",
    "movetype": ""

},{
    "hero:id: 97,
    "name": "Lucius",
    "basehp": ,
    "baseatk": ,
    "basespd": ,
    "basedef": ,
    "baseres": ,
    "color": "",
    "weapontype": "",
    "movetype": ""

},{
    "hero:id: 98,
    "name": "Maria",
    "basehp": ,
    "baseatk": ,
    "basespd": ,
    "basedef": ,
    "baseres": ,
    "color": "",
    "weapontype": "",
    "movetype": ""

},{
    "hero:id: 99,
    "name": "Matthew",
    "basehp": ,
    "baseatk": ,
    "basespd": ,
    "basedef": ,
    "baseres": ,
    "color": "",
    "weapontype": "",
    "movetype": ""

},{
    "hero:id: 100,
    "name": "Niles",
    "basehp": ,
    "baseatk": ,
    "basespd": ,
    "basedef": ,
    "baseres": ,
    "color": "",
    "weapontype": "",
    "movetype": ""

},{
    "hero:id: 101,
    "name": "Priscilla",
    "basehp": ,
    "baseatk": ,
    "basespd": ,
    "basedef": ,
    "baseres": ,
    "color": "",
    "weapontype": "",
    "movetype": ""

},{
    "hero:id: ,
    "name": "",
    "basehp": ,
    "baseatk": ,
    "basespd": ,
    "basedef": ,
    "baseres": ,
    "color": "",
    "weapontype": "",
    "movetype": "",

},{
    "hero:id: ,
    "name": "",
    "basehp": ,
    "baseatk": ,
    "basespd": ,
    "basedef": ,
    "baseres": ,
    "color": "",
    "weapontype": "",
    "movetype": "",

},{
    "hero:id: ,
    "name": "",
    "basehp": ,
    "baseatk": ,
    "basespd": ,
    "basedef": ,
    "baseres": ,
    "color": "",
    "weapontype": "",
    "movetype": "",

},{
    "hero:id: ,
    "name": "",
    "basehp": ,
    "baseatk": ,
    "basespd": ,
    "basedef": ,
    "baseres": ,
    "color": "",
    "weapontype": "",
    "movetype": "",

},{
    "hero:id: ,
    "name": "",
    "basehp": ,
    "baseatk": ,
    "basespd": ,
    "basedef": ,
    "baseres": ,
    "color": "",
    "weapontype": "",
    "movetype": "",

},{
    "hero:id: ,
    "name": "",
    "basehp": ,
    "baseatk": ,
    "basespd": ,
    "basedef": ,
    "baseres": ,
    "color": "",
    "weapontype": "",
    "movetype": "",

},{
    "hero:id: ,
    "name": "",
    "basehp": ,
    "baseatk": ,
    "basespd": ,
    "basedef": ,
    "baseres": ,
    "color": "",
    "weapontype": "",
    "movetype": "",

},{
    "hero:id: ,
    "name": "",
    "basehp": ,
    "baseatk": ,
    "basespd": ,
    "basedef": ,
    "baseres": ,
    "color": "",
    "weapontype": "",
    "movetype": "",

},{
    "hero:id: ,
    "name": "",
    "basehp": ,
    "baseatk": ,
    "basespd": ,
    "basedef": ,
    "baseres": ,
    "color": "",
    "weapontype": "",
    "movetype": "",

},{
    "hero:id: ,
    "name": "",
    "basehp": ,
    "baseatk": ,
    "basespd": ,
    "basedef": ,
    "baseres": ,
    "color": "",
    "weapontype": "",
    "movetype": "",

},{
    "hero:id: ,
    "name": "",
    "basehp": ,
    "baseatk": ,
    "basespd": ,
    "basedef": ,
    "baseres": ,
    "color": "",
    "weapontype": "",
    "movetype": "",

},{
    "hero:id: ,
    "name": "",
    "basehp": ,
    "baseatk": ,
    "basespd": ,
    "basedef": ,
    "baseres": ,
    "color": "",
    "weapontype": "",
    "movetype": "",

},{
    "hero:id: ,
    "name": "",
    "basehp": ,
    "baseatk": ,
    "basespd": ,
    "basedef": ,
    "baseres": ,
    "color": "",
    "weapontype": "",
    "movetype": "",

},{
    "hero:id: ,
    "name": "",
    "basehp": ,
    "baseatk": ,
    "basespd": ,
    "basedef": ,
    "baseres": ,
    "color": "",
    "weapontype": "",
    "movetype": "",

},
